eseas/__init__.py
eseas/core/__init__.py
eseas/core/_general_params.py
eseas/core/_options.py
eseas/core/_regex_utils.py
eseas/core/create_bat_command.py
eseas/core/cruncher_classes.py
eseas/core/demetra.py
eseas/core/demetra_caller.py
eseas/core/demetra_file_naming.py
eseas/core/df_operations.py
eseas/core/folder_class.py
eseas/core/github_actions.py
eseas/core/java_environ.py
eseas/core/json_ops.py
eseas/core/picker_classes.py
eseas/core/seas_testing_utils.py
eseas/core/seas_utils.py
eseas/core/seasonal_adv_utils.py
eseas/core/seasonal_general.py
eseas/core/seasonal_options.py
eseas/core/utils_general2.py
eseas/data_for_testing/__init__.py
eseas/data_for_testing/csv_content.py
eseas/data_for_testing/some_data.py
eseas/tests/__init__.py
eseas/tests/test_crunch.py
eseas/tests/test_env_file_run.py
eseas/tests/test_java_env.py
eseas/tests/test_main.py
eseas/tests/test_utils.py
eseas-1.0.4.dist-info/METADATA
eseas-1.0.4.dist-info/WHEEL
eseas-1.0.4.dist-info/licenses/LICENSE
eseas-1.0.4.dist-info/RECORD
