Metadata-Version: 2.4
Name: eseas
Version: 1.0.4
Summary: eseas is a Python package that serves as a wrapper for the jwsacruncher Java package. This tool allows users to process Demetra workspace XML files, create batch files, execute them, and collect the desired outputs into individual Excel files.
Project-URL: Repository, https://github.com/SermetPekin/eseas-repo
Project-URL: Documentation, https://eseas-repo.readthedocs.io/en/latest/home.html
Author-email: Sermet Pekin <sermet.pekin@gmail.com>
License: EUPL-1.2
License-File: LICENSE
Keywords: Demetra,data processing,jwsacruncher,seasonal adjustment
Requires-Python: >=3.9
Requires-Dist: evdspy>=1.1.41
